verbal/__init__.py
verbal/argh.py
verbal/istring.py
verbal/logging.py
verbal/loggly.py
verbal/mongolog.py
verbal/mongolog.py.orig
verbal/test/__init__.py
verbal/test/test_istring.py
verbal/test/test_loggly.py
python_verbal-20200120.1.dist-info/METADATA
python_verbal-20200120.1.dist-info/WHEEL
python_verbal-20200120.1.dist-info/entry_points.txt
python_verbal-20200120.1.dist-info/top_level.txt
python_verbal-20200120.1.dist-info/RECORD
